README.rst
setup.py
paths_graph/__init__.py
paths_graph/api.py
paths_graph/cfpg.py
paths_graph/paths_tree.py
paths_graph/pg.py
paths_graph/pre_cfpg.py
paths_graph.egg-info/PKG-INFO
paths_graph.egg-info/SOURCES.txt
paths_graph.egg-info/dependency_links.txt
paths_graph.egg-info/requires.txt
paths_graph.egg-info/top_level.txt